dadaptation/__init__.py
dadaptation/dadapt_adagrad.py
dadaptation/dadapt_adam.py
dadaptation/dadapt_adan.py
dadaptation/dadapt_sgd.py
dadaptation/experimental/__init__.py
dadaptation/experimental/dadapt_adam_ip.py
dadaptation/experimental/dadapt_adan_ip.py
dadaptation/experimental/dadapt_sgd_ip.py
dadaptation-2.0.dist-info/LICENSE
dadaptation-2.0.dist-info/METADATA
dadaptation-2.0.dist-info/WHEEL
dadaptation-2.0.dist-info/top_level.txt
dadaptation-2.0.dist-info/RECORD
