Metadata-Version: 2.1
Name: dadaptation
Version: 2.0
Summary: Learning Rate Free Learning for Adam, SGD and AdaGrad
Home-page: https://github.com/facebookresearch/dadaptation
Author: Aaron Defazio
Author-email: adefazio@meta.com
Classifier: Programming Language :: Python :: 3
Classifier: License :: OSI Approved :: MIT License
Classifier: Operating System :: OS Independent
Requires-Python: >=3.6
License-File: LICENSE
